[
    { "id": 1, "sede": "Caracas", "producto": "Aceite 10W-40 Sintético", "precio": 12.5, "stock": 150 },
    { "id": 2, "sede": "Caracas", "producto": "Aceite 20W-50 Mineral", "precio": 8.5, "stock": 200 },
    { "id": 3, "sede": "Caracas", "producto": "Filtro de Aceite Gold", "precio": 5.0, "stock": 80 },
    { "id": 4, "sede": "Caracas", "producto": "Kit de Estoperas", "precio": 15.0, "stock": 40 },
    { "id": 5, "sede": "Caracas", "producto": "Pistón Standar V6", "precio": 45.0, "stock": 24 },
    { "id": 6, "sede": "Caracas", "producto": "Aceite para Transmisión", "precio": 14.0, "stock": 60 },
    { "id": 7, "sede": "Caracas", "producto": "Limpiador de Inyectores", "precio": 6.5, "stock": 100 },
    { "id": 8, "sede": "Caracas", "producto": "Goma de Válvula", "precio": 2.0, "stock": 500 },
    { "id": 9, "sede": "Caracas", "producto": "Empacadura de Cámara", "precio": 25.0, "stock": 30 },
    { "id": 10, "sede": "Caracas", "producto": "Refrigerante Rojo 50/50", "precio": 10.0, "stock": 85 },

    { "id": 11, "sede": "Valencia", "producto": "Aceite 10W-40 Sintético", "precio": 12.0, "stock": 300 },
    { "id": 12, "sede": "Valencia", "producto": "Aceite 15W-40 Diesel", "precio": 9.5, "stock": 180 },
    { "id": 13, "sede": "Valencia", "producto": "Bomba de Aceite", "precio": 55.0, "stock": 15 },
    { "id": 14, "sede": "Valencia", "producto": "Kit de Tiempo", "precio": 85.0, "stock": 10 },
    { "id": 15, "sede": "Valencia", "producto": "Anillos de Pistón", "precio": 35.0, "stock": 45 },
    { "id": 16, "sede": "Valencia", "producto": "Goma Soporte Motor", "precio": 18.0, "stock": 50 },
    { "id": 17, "sede": "Valencia", "producto": "Aceite 5W-30 Full", "precio": 15.0, "stock": 90 },
    { "id": 18, "sede": "Valencia", "producto": "Grasa Industrial Azul", "precio": 7.0, "stock": 120 },
    { "id": 19, "sede": "Valencia", "producto": "Válvula de Presión", "precio": 12.0, "stock": 25 },
    { "id": 20, "sede": "Valencia", "producto": "Aceite Hidráulico", "precio": 11.0, "stock": 75 },

    { "id": 21, "sede": "Maracaibo", "producto": "Aceite 20W-50 Alto KM", "precio": 9.0, "stock": 400 },
    { "id": 22, "sede": "Maracaibo", "producto": "Filtro Gasolina", "precio": 4.5, "stock": 150 },
    { "id": 23, "sede": "Maracaibo", "producto": "Empacadura Tapa Válvula", "precio": 12.0, "stock": 60 },
    { "id": 24, "sede": "Maracaibo", "producto": "Pistón +0.20", "precio": 48.0, "stock": 12 },
    { "id": 25, "sede": "Maracaibo", "producto": "Aceite 10W-30", "precio": 13.0, "stock": 110 },
    { "id": 26, "sede": "Maracaibo", "producto": "Liga de Frenos Dot4", "precio": 8.0, "stock": 200 },
    { "id": 27, "sede": "Maracaibo", "producto": "Estopera Trasera", "precio": 9.0, "stock": 80 },
    { "id": 28, "sede": "Maracaibo", "producto": "Kit de Gomas de Suspensión", "precio": 30.0, "stock": 35 },
    { "id": 29, "sede": "Maracaibo", "producto": "Sellador de Fugas", "precio": 14.0, "stock": 50 },
    { "id": 30, "sede": "Maracaibo", "producto": "Aceite Moto 4T", "precio": 7.5, "stock": 300 },

    { "id": 31, "sede": "Puerto Ordaz", "producto": "Aceite Sintético 10W-40", "precio": 13.0, "stock": 100 },
    { "id": 32, "sede": "Puerto Ordaz", "producto": "Aceite Industrial Grado 68", "precio": 250.0, "stock": 5 },
    { "id": 33, "sede": "Puerto Ordaz", "producto": "Pistón Cummins Heavy", "precio": 120.0, "stock": 8 },
    { "id": 34, "sede": "Puerto Ordaz", "producto": "Kit de Gomas Maquinaria", "precio": 45.0, "stock": 20 },
    { "id": 35, "sede": "Puerto Ordaz", "producto": "Aceite 15W-40 Diesel Galón", "precio": 35.0, "stock": 50 },
    { "id": 36, "sede": "Puerto Ordaz", "producto": "Filtro Aire Pesado", "precio": 22.0, "stock": 15 },
    { "id": 37, "sede": "Puerto Ordaz", "producto": "Grasa Grafitada", "precio": 12.0, "stock": 40 },
    { "id": 38, "sede": "Puerto Ordaz", "producto": "Estopera de Cigüeñal", "precio": 18.0, "stock": 30 },
    { "id": 39, "sede": "Puerto Ordaz", "producto": "Bomba de Agua", "precio": 65.0, "stock": 12 },
    { "id": 40, "sede": "Puerto Ordaz", "producto": "Líquido de Dirección", "precio": 9.5, "stock": 60 }
]
